{
  "generated": "2025-12-26T22:08:13.920Z",
  "date": "2025-12-26",
  "totalWords": 20,
  "words": [
    {
      "id": "w02544",
      "word": "glacier",
      "type": "single",
      "chapterIndex": 16,
      "globalIndex": 2544,
      "chapter": "ch103",
      "chapterName": "认知词汇 自然分类 \"厄尔尼诺\"现象",
      "pronunciation": {
        "us": "/ˈɡleɪʃər/"
      },
      "meanings": [
        {
          "pos": "n.",
          "zh": "冰川",
          "en": "A large, slow-moving mass of ice that forms from compacted snow."
        },
        {
          "pos": "n.",
          "zh": "冰川",
          "en": "A persistent body of dense ice that covers the land and moves under its own weight."
        }
      ],
      "examples": [
        {
          "en": "The glacier slowly melted due to rising global temperatures.",
          "zh": "由于全球气温上升，冰川缓慢融化。"
        },
        {
          "en": "Scientists study glaciers to understand climate change better.",
          "zh": "科学家研究冰川以更好地了解气候变化。"
        }
      ],
      "memoryTips": {
        "association": "Think of 'glacier' as 'glassy' ice moving slowly down a mountain."
      },
      "audioUrl": "https://dict.youdao.com/dictvoice?audio=glacier&type=2"
    },
    {
      "id": "w02724",
      "word": "forest clearing",
      "type": "phrase",
      "chapterIndex": 16,
      "globalIndex": 2724,
      "chapter": "ch107",
      "chapterName": "认知词汇 自然分类 热带雨林",
      "pronunciation": {
        "us": "/ˈfɔːrɪst ˈklɪərɪŋ/"
      },
      "meanings": [
        {
          "pos": "n.",
          "zh": "森林空地",
          "en": "An open area in a forest where there are no trees."
        },
        {
          "pos": "n.",
          "zh": "森林开垦",
          "en": "The act of clearing trees from a part of a forest."
        }
      ],
      "examples": [
        {
          "en": "The deer grazed peacefully in the forest clearing.",
          "zh": "鹿在森林空地上安静地吃草。"
        },
        {
          "en": "The forest clearing was perfect for our picnic.",
          "zh": "森林空地非常适合我们的野餐。"
        }
      ],
      "memoryTips": {
        "association": "Think of a 'clear' space in a 'forest' where you can see the sky."
      },
      "audioUrl": "https://dict.youdao.com/dictvoice?audio=forest%20clearing&type=2"
    },
    {
      "id": "w00760",
      "word": "timid",
      "type": "single",
      "chapterIndex": 20,
      "globalIndex": 760,
      "chapter": "ch038",
      "chapterName": "基本词汇 形容词和副词400 Unit 18",
      "pronunciation": {
        "us": "/ˈtɪmɪd/"
      },
      "meanings": [
        {
          "pos": "adj.",
          "zh": "胆怯的",
          "en": "Feeling shy or lacking confidence."
        },
        {
          "pos": "adj.",
          "zh": "胆小的",
          "en": "Easily frightened or not brave."
        }
      ],
      "examples": [
        {
          "en": "The timid child hesitated to speak in front of the class.",
          "zh": "那个胆怯的孩子在班上犹豫着不敢发言。"
        },
        {
          "en": "She gave a timid smile when she met new people.",
          "zh": "她见到新朋友时露出了一个胆怯的微笑。"
        }
      ],
      "memoryTips": {
        "association": "Think of a timid mouse hiding away, too scared to come out."
      },
      "audioUrl": "https://dict.youdao.com/dictvoice?audio=timid&type=2"
    },
    {
      "id": "w01975",
      "word": "commercial fishery",
      "type": "phrase",
      "chapterIndex": 75,
      "globalIndex": 1975,
      "chapter": "ch096",
      "chapterName": "认知词汇 动物分类 常考生物",
      "pronunciation": {
        "us": "/kəˈmɜːrʃəl ˈfɪʃəri/"
      },
      "meanings": [
        {
          "pos": "n.",
          "zh": "商业渔业",
          "en": "A type of fishing that is done for profit and sale."
        },
        {
          "pos": "n.",
          "zh": "商业捕鱼场",
          "en": "A place where fish are caught and sold for business."
        }
      ],
      "examples": [
        {
          "en": "The commercial fishery industry plays a vital role in the economy.",
          "zh": "商业渔业在经济中扮演着重要角色。"
        },
        {
          "en": "Sustainable practices are essential for the future of commercial fisheries.",
          "zh": "可持续的做法对商业渔业的未来至关重要。"
        }
      ],
      "audioUrl": "https://dict.youdao.com/dictvoice?audio=commercial%20fishery&type=2"
    },
    {
      "id": "w01849",
      "word": "heredity",
      "type": "single",
      "chapterIndex": 9,
      "globalIndex": 1849,
      "chapter": "ch093",
      "chapterName": "核心词汇 健康话题 Unit 3",
      "pronunciation": {
        "us": "/həˈrɛdəti/"
      },
      "meanings": [
        {
          "pos": "n.",
          "zh": "遗传",
          "en": "The passing of traits from parents to their children."
        },
        {
          "pos": "n.",
          "zh": "遗传特征",
          "en": "The characteristics that are inherited from one's ancestors."
        }
      ],
      "examples": [
        {
          "en": "Heredity plays a significant role in determining physical traits.",
          "zh": "遗传在决定身体特征中起着重要作用。"
        },
        {
          "en": "Many diseases can be linked to heredity and genetic factors.",
          "zh": "许多疾病可以与遗传和遗传因素相关联。"
        }
      ],
      "memoryTips": {
        "etymology": "The word 'heredity' comes from the Latin 'hereditas', meaning 'inheritance'."
      },
      "audioUrl": "https://dict.youdao.com/dictvoice?audio=heredity&type=2"
    },
    {
      "id": "w01858",
      "word": "infection",
      "type": "single",
      "chapterIndex": 18,
      "globalIndex": 1858,
      "chapter": "ch093",
      "chapterName": "核心词汇 健康话题 Unit 3",
      "pronunciation": {
        "us": "/ɪnˈfɛkʃən/"
      },
      "meanings": [
        {
          "pos": "n.",
          "zh": "感染",
          "en": "The invasion of the body by harmful organisms that cause illness."
        },
        {
          "pos": "n.",
          "zh": "传染病",
          "en": "A disease that can be spread from one person to another."
        }
      ],
      "examples": [
        {
          "en": "He contracted a serious infection after the surgery.",
          "zh": "他在手术后感染了严重的感染。"
        },
        {
          "en": "Vaccination helps prevent the spread of infectious diseases.",
          "zh": "疫苗接种有助于防止传染病的传播。"
        }
      ],
      "memoryTips": {
        "etymology": "The word 'infection' comes from the Latin 'infectio', meaning 'to taint or dye'."
      },
      "audioUrl": "https://dict.youdao.com/dictvoice?audio=infection&type=2"
    },
    {
      "id": "w00088",
      "word": "demonstrate",
      "type": "single",
      "chapterIndex": 8,
      "globalIndex": 88,
      "chapter": "ch005",
      "chapterName": "基本词汇 动词200 Unit 5",
      "pronunciation": {
        "us": "/ˈdɛmənˌstreɪt/"
      },
      "meanings": [
        {
          "pos": "v.",
          "zh": "展示",
          "en": "To show clearly or prove something."
        },
        {
          "pos": "v.",
          "zh": "演示",
          "en": "To explain how something works by showing it."
        }
      ],
      "examples": [
        {
          "en": "The teacher will demonstrate the experiment to the class.",
          "zh": "老师将向班级展示这个实验。"
        },
        {
          "en": "The results clearly demonstrate the effectiveness of the new method.",
          "zh": "结果清楚地展示了新方法的有效性。"
        }
      ],
      "memoryTips": {
        "association": "Think of 'demonstrate' as 'demo' + 'strate', where 'demo' is a common way to show or explain."
      },
      "audioUrl": "https://dict.youdao.com/dictvoice?audio=demonstrate&type=2"
    },
    {
      "id": "w00394",
      "word": "warning",
      "type": "single",
      "chapterIndex": 14,
      "globalIndex": 394,
      "chapter": "ch020",
      "chapterName": "基本词汇 名词200 Unit 10",
      "pronunciation": {
        "us": "/ˈwɔrnɪŋ/"
      },
      "meanings": [
        {
          "pos": "n.",
          "zh": "警告",
          "en": "A statement that something bad may happen."
        },
        {
          "pos": "v.",
          "zh": "警告",
          "en": "To tell someone that something bad might happen."
        }
      ],
      "examples": [
        {
          "en": "The warning about the storm was announced on the radio.",
          "zh": "关于风暴的警告在广播中宣布。"
        },
        {
          "en": "She gave him a warning before he made a big mistake.",
          "zh": "在他犯大错之前，她给了他一个警告。"
        }
      ],
      "memoryTips": {
        "association": "Think of a 'warning' sign that alerts you to danger, like a stop sign."
      },
      "audioUrl": "https://dict.youdao.com/dictvoice?audio=warning&type=2"
    },
    {
      "id": "w00500",
      "word": "desirable",
      "type": "single",
      "chapterIndex": 20,
      "globalIndex": 500,
      "chapter": "ch025",
      "chapterName": "基本词汇 形容词和副词400 Unit 5",
      "pronunciation": {
        "us": "/dɪˈzaɪərəbəl/"
      },
      "meanings": [
        {
          "pos": "adj.",
          "zh": "令人向往的",
          "en": "Something that is wanted or wished for."
        },
        {
          "pos": "adj.",
          "zh": "值得拥有的",
          "en": "Something that is attractive or appealing."
        }
      ],
      "examples": [
        {
          "en": "A desirable job often offers great benefits and opportunities.",
          "zh": "一个理想的工作通常提供很好的福利和机会。"
        },
        {
          "en": "Living in a safe neighborhood is considered very desirable.",
          "zh": "居住在安全的社区被认为是非常理想的。"
        }
      ],
      "memoryTips": {
        "association": "Think of 'desire' in 'desirable', as it relates to wanting something."
      },
      "audioUrl": "https://dict.youdao.com/dictvoice?audio=desirable&type=2"
    },
    {
      "id": "w01889",
      "word": "strain",
      "type": "single",
      "chapterIndex": 9,
      "globalIndex": 1889,
      "chapter": "ch095",
      "chapterName": "核心词汇 健康话题 Unit 5",
      "pronunciation": {
        "us": "/streɪn/"
      },
      "meanings": [
        {
          "pos": "v.",
          "zh": "使紧绷",
          "en": "To make something tight or tense."
        },
        {
          "pos": "n.",
          "zh": "压力",
          "en": "A feeling of worry or pressure."
        }
      ],
      "examples": [
        {
          "en": "She felt a strain in her back after lifting the heavy box.",
          "zh": "她在抬起重箱子后感到背部有压力。"
        },
        {
          "en": "The strain of the exam caused him a lot of anxiety.",
          "zh": "考试的压力让他感到非常焦虑。"
        }
      ],
      "memoryTips": {
        "association": "Think of 'strain' as stretching a rubber band, which can become tight or break under too much pressure."
      },
      "audioUrl": "https://dict.youdao.com/dictvoice?audio=strain&type=2"
    },
    {
      "id": "w01702",
      "word": "addiction",
      "type": "single",
      "chapterIndex": 2,
      "globalIndex": 1702,
      "chapter": "ch086",
      "chapterName": "核心词汇 法制与犯罪 Unit 1",
      "pronunciation": {
        "us": "/əˈdɪkʃən/"
      },
      "meanings": [
        {
          "pos": "n.",
          "zh": "上瘾，成瘾",
          "en": "A strong need to do something regularly."
        },
        {
          "pos": "n.",
          "zh": "嗜好，沉迷",
          "en": "A habit that is hard to control and affects life."
        }
      ],
      "examples": [
        {
          "en": "His addiction to video games affected his school performance.",
          "zh": "他对视频游戏的上瘾影响了他的学业表现。"
        },
        {
          "en": "Many people struggle with addiction to cigarettes or alcohol.",
          "zh": "许多人在与香烟或酒精的成瘾斗争。"
        }
      ],
      "memoryTips": {
        "etymology": "The word 'addiction' comes from Latin 'addictio', meaning a surrender or dedication.",
        "association": "Think of 'addict' as someone who is 'addicted' to something they can't live without."
      },
      "audioUrl": "https://dict.youdao.com/dictvoice?audio=addiction&type=2"
    },
    {
      "id": "w01903",
      "word": "arboreal",
      "type": "single",
      "chapterIndex": 3,
      "globalIndex": 1903,
      "chapter": "ch096",
      "chapterName": "认知词汇 动物分类 常考生物",
      "pronunciation": {
        "us": "/ɑːrˈbɔːr.i.əl/"
      },
      "meanings": [
        {
          "pos": "adj.",
          "zh": "树栖的",
          "en": "Relating to trees; living in trees."
        },
        {
          "pos": "adj.",
          "zh": "树木生长的",
          "en": "Describing animals that primarily inhabit or move through trees."
        }
      ],
      "examples": [
        {
          "en": "Monkeys are often classified as arboreal animals due to their tree-dwelling habits.",
          "zh": "猴子通常被归类为树栖动物，因为它们的栖息习惯在树上。"
        },
        {
          "en": "The arboreal lifestyle of sloths makes them unique among mammals.",
          "zh": "树栖生活方式使树懒在哺乳动物中独树一帜。"
        }
      ],
      "memoryTips": {
        "association": "Think of 'arbor', which means tree, to remember 'arboreal' relates to trees."
      },
      "audioUrl": "https://dict.youdao.com/dictvoice?audio=arboreal&type=2"
    },
    {
      "id": "w01695",
      "word": "vigour",
      "type": "single",
      "chapterIndex": 15,
      "globalIndex": 1695,
      "chapter": "ch085",
      "chapterName": "核心词汇 工作与生活 Unit 5",
      "pronunciation": {
        "us": "/ˈvɪɡər/"
      },
      "meanings": [
        {
          "pos": "n.",
          "zh": "活力；精力",
          "en": "The physical strength and energy to do something."
        },
        {
          "pos": "n.",
          "zh": "力量；强度",
          "en": "The intensity or force of something."
        }
      ],
      "examples": [
        {
          "en": "She approached the challenge with great vigour and determination.",
          "zh": "她以极大的活力和决心面对这个挑战。"
        },
        {
          "en": "The team played with vigour, showcasing their skills on the field.",
          "zh": "球队表现出活力，展示了他们在场上的技能。"
        }
      ],
      "audioUrl": "https://dict.youdao.com/dictvoice?audio=vigour&type=2"
    },
    {
      "id": "w01694",
      "word": "vice",
      "type": "single",
      "chapterIndex": 14,
      "globalIndex": 1694,
      "chapter": "ch085",
      "chapterName": "核心词汇 工作与生活 Unit 5",
      "pronunciation": {
        "us": "/vaɪs/"
      },
      "meanings": [
        {
          "pos": "n.",
          "zh": "恶习",
          "en": "A bad habit or immoral behavior."
        },
        {
          "pos": "n.",
          "zh": "副手",
          "en": "A person who acts as a substitute or assistant."
        }
      ],
      "examples": [
        {
          "en": "His vice of gambling caused many problems in his life.",
          "zh": "他赌博的恶习给他的生活带来了很多问题。"
        },
        {
          "en": "The vice president will attend the meeting tomorrow.",
          "zh": "副总统明天将参加会议。"
        }
      ],
      "memoryTips": {
        "etymology": "The word 'vice' comes from the Latin 'vitium', meaning 'fault' or 'defect'."
      },
      "audioUrl": "https://dict.youdao.com/dictvoice?audio=vice&type=2"
    },
    {
      "id": "w01715",
      "word": "confidence",
      "type": "single",
      "chapterIndex": 15,
      "globalIndex": 1715,
      "chapter": "ch086",
      "chapterName": "核心词汇 法制与犯罪 Unit 1",
      "pronunciation": {
        "us": "/ˈkɒnfɪdəns/"
      },
      "meanings": [
        {
          "pos": "n.",
          "zh": "信心，自信",
          "en": "A feeling of trust in one's abilities or qualities."
        },
        {
          "pos": "n.",
          "zh": "信任，依赖",
          "en": "The belief that someone or something is reliable."
        }
      ],
      "examples": [
        {
          "en": "She spoke with confidence during her presentation to the class.",
          "zh": "她在课堂上的演讲中充满自信。"
        },
        {
          "en": "Building confidence is essential for success in any field.",
          "zh": "建立自信对任何领域的成功至关重要。"
        }
      ],
      "audioUrl": "https://dict.youdao.com/dictvoice?audio=confidence&type=2"
    },
    {
      "id": "w01343",
      "word": "peer",
      "type": "single",
      "chapterIndex": 3,
      "globalIndex": 1343,
      "chapter": "ch068",
      "chapterName": "核心词汇 青少年教育 Unit 8",
      "pronunciation": {
        "us": "/pɪr/"
      },
      "meanings": [
        {
          "pos": "n.",
          "zh": "同龄人，同行",
          "en": "A person who is of similar age or status as another."
        },
        {
          "pos": "v.",
          "zh": "凝视，审视",
          "en": "To look closely or carefully at something."
        }
      ],
      "examples": [
        {
          "en": "Many teenagers feel pressured to fit in with their peers.",
          "zh": "许多青少年感到被同龄人所施加的压力，想要融入其中。"
        },
        {
          "en": "She decided to peer through the window to see what was happening.",
          "zh": "她决定透过窗户仔细查看发生了什么。"
        }
      ],
      "memoryTips": {
        "association": "Think of 'peer' as 'pair', referring to people who are alike, like a pair of friends."
      },
      "audioUrl": "https://dict.youdao.com/dictvoice?audio=peer&type=2"
    },
    {
      "id": "w00973",
      "word": "rainfall",
      "type": "single",
      "chapterIndex": 13,
      "globalIndex": 973,
      "chapter": "ch049",
      "chapterName": "核心词汇 环境保护 Unit 4",
      "pronunciation": {
        "us": "/ˈreɪnˌfɔl/"
      },
      "meanings": [
        {
          "pos": "n.",
          "zh": "降雨量",
          "en": "The amount of rain that falls in a specific area."
        },
        {
          "pos": "n.",
          "zh": "降雨",
          "en": "The act of rain falling from the sky."
        }
      ],
      "examples": [
        {
          "en": "Heavy rainfall can lead to flooding in low-lying areas.",
          "zh": "大雨可能导致低洼地区洪水泛滥。"
        },
        {
          "en": "The rainfall this year is higher than the average for the region.",
          "zh": "今年的降雨量高于该地区的平均水平。"
        }
      ],
      "memoryTips": {
        "association": "Think of 'rain' falling from the sky and 'fall' as it descends."
      },
      "audioUrl": "https://dict.youdao.com/dictvoice?audio=rainfall&type=2"
    },
    {
      "id": "w00302",
      "word": "lack",
      "type": "single",
      "chapterIndex": 2,
      "globalIndex": 302,
      "chapter": "ch016",
      "chapterName": "基本词汇 名词200 Unit 6",
      "pronunciation": {
        "us": "/læk/"
      },
      "meanings": [
        {
          "pos": "v.",
          "zh": "缺乏",
          "en": "To not have enough of something."
        },
        {
          "pos": "n.",
          "zh": "缺乏",
          "en": "The state of not having enough of something."
        }
      ],
      "examples": [
        {
          "en": "Many children suffer from a lack of proper nutrition.",
          "zh": "许多孩子缺乏适当的营养。"
        },
        {
          "en": "The project failed due to a lack of funding and support.",
          "zh": "该项目由于缺乏资金和支持而失败。"
        }
      ],
      "memoryTips": {
        "association": "Think of 'lack' as 'lacking' something important in your life."
      },
      "audioUrl": "https://dict.youdao.com/dictvoice?audio=lack&type=2"
    },
    {
      "id": "w00512",
      "word": "discontented",
      "type": "single",
      "chapterIndex": 12,
      "globalIndex": 512,
      "chapter": "ch026",
      "chapterName": "基本词汇 形容词和副词400 Unit 6",
      "pronunciation": {
        "us": "/ˌdɪs.kənˈtɛn.tɪd/"
      },
      "meanings": [
        {
          "pos": "adj.",
          "zh": "不满的， dissatisfied",
          "en": "Feeling unhappy or dissatisfied with the current situation."
        },
        {
          "pos": "n.",
          "zh": "不满， dissatisfaction",
          "en": "A feeling of unhappiness or dissatisfaction."
        }
      ],
      "examples": [
        {
          "en": "Many employees are discontented with their working conditions.",
          "zh": "许多员工对他们的工作条件感到不满。"
        },
        {
          "en": "The citizens expressed their discontented views during the meeting.",
          "zh": "市民在会议上表达了他们的不满意见。"
        }
      ],
      "memoryTips": {
        "etymology": "The word 'discontented' comes from the prefix 'dis-' meaning 'not' and 'contented' which means 'satisfied'.",
        "association": "Think of 'discontented' as 'not content', which helps remember its meaning of dissatisfaction."
      },
      "audioUrl": "https://dict.youdao.com/dictvoice?audio=discontented&type=2"
    },
    {
      "id": "w00392",
      "word": "vision",
      "type": "single",
      "chapterIndex": 12,
      "globalIndex": 392,
      "chapter": "ch020",
      "chapterName": "基本词汇 名词200 Unit 10",
      "pronunciation": {
        "us": "/ˈvɪʒ.ən/"
      },
      "meanings": [
        {
          "pos": "n.",
          "zh": "视力；愿景",
          "en": "The ability to see or a plan for the future."
        },
        {
          "pos": "v.",
          "zh": "想象；设想",
          "en": "To imagine or conceive something in the mind."
        }
      ],
      "examples": [
        {
          "en": "Her vision for the project inspired everyone on the team.",
          "zh": "她对项目的愿景激励了团队中的每一个人。"
        },
        {
          "en": "He has a clear vision of what he wants to achieve in life.",
          "zh": "他对自己想要在生活中实现的目标有清晰的愿景。"
        }
      ],
      "memoryTips": {
        "etymology": "The word 'vision' comes from the Latin 'visio', meaning 'sight' or 'to see'."
      },
      "audioUrl": "https://dict.youdao.com/dictvoice?audio=vision&type=2"
    }
  ]
}