{
  "generated": "2025-11-04T22:07:50.077Z",
  "pair": 8,
  "count": 2,
  "words": [
    {
      "word": "abuse",
      "pronunciation": "/əˈbjuz/",
      "meanings": [
        {
          "pos": "v.",
          "zh": "滥用；虐待",
          "en": "To use something in a harmful or wrong way."
        },
        {
          "pos": "n.",
          "zh": "虐待；滥用",
          "en": "The act of treating someone or something badly."
        }
      ],
      "examples": [
        {
          "en": "The organization works to prevent child abuse in our community.",
          "zh": "该组织致力于防止我们社区的儿童虐待。"
        },
        {
          "en": "Many people suffer from substance abuse due to addiction.",
          "zh": "许多人因成瘾而遭受药物滥用。"
        }
      ],
      "memoryTips": {
        "etymology": "The word 'abuse' comes from the Latin 'abusus', meaning 'to use wrongly'."
      },
      "audioUrl": "https://dict.youdao.com/dictvoice?audio=abuse&type=2",
      "chapter": "基本词汇 动词200 Unit 1"
    },
    {
      "word": "casualties",
      "pronunciation": "/ˈkæʒ.u.əl.tiz/",
      "meanings": [
        {
          "pos": "n.",
          "zh": "伤亡人员",
          "en": "People who are killed or injured in a war or accident."
        },
        {
          "pos": "n.",
          "zh": "损失",
          "en": "The total number of people affected by an event, particularly in terms of injuries or deaths."
        }
      ],
      "examples": [
        {
          "en": "The earthquake caused many casualties and widespread destruction.",
          "zh": "这场地震造成了许多伤亡和广泛的破坏。"
        },
        {
          "en": "The report highlighted the casualties from the recent conflict.",
          "zh": "报告强调了最近冲突中的伤亡情况。"
        }
      ],
      "memoryTips": {},
      "audioUrl": "https://dict.youdao.com/dictvoice?audio=casualties&type=2",
      "chapter": "认知词汇 自然分类 地震"
    }
  ]
}