{
  "generated": "2025-12-19T22:08:31.376Z",
  "pair": 7,
  "count": 2,
  "words": [
    {
      "word": "stability",
      "pronunciation": "/stəˈbɪləti/",
      "meanings": [
        {
          "pos": "n.",
          "zh": "稳定性",
          "en": "The quality of being steady and not changing."
        },
        {
          "pos": "n.",
          "zh": "稳定状态",
          "en": "The state of being secure and not likely to fall or change."
        }
      ],
      "examples": [
        {
          "en": "The stability of the economy is crucial for long-term growth.",
          "zh": "经济的稳定性对长期增长至关重要。"
        },
        {
          "en": "She values the stability of her job above all else.",
          "zh": "她最看重的是工作的稳定性。"
        }
      ],
      "memoryTips": {
        "association": "Think of a stable table that doesn't wobble; it stays steady."
      },
      "audioUrl": "https://dict.youdao.com/dictvoice?audio=stability&type=2",
      "chapter": "核心词汇 民主与权利 Unit 5"
    },
    {
      "word": "anticoagulant",
      "pronunciation": "/ˌæntiˈkoʊ.ə.ɡə.lənt/",
      "meanings": [
        {
          "pos": "n.",
          "zh": "抗凝剂",
          "en": "A substance that prevents blood from clotting."
        }
      ],
      "examples": [
        {
          "en": "Doctors often prescribe anticoagulants to reduce the risk of strokes.",
          "zh": "医生常常开抗凝剂来降低中风风险。"
        },
        {
          "en": "Taking anticoagulants requires careful monitoring of blood levels.",
          "zh": "服用抗凝剂需要仔细监测血液水平。"
        }
      ],
      "memoryTips": {
        "association": "Think of 'anti' as against, and 'coagulant' as something that clots. So, anticoagulant is something that works against clotting."
      },
      "audioUrl": "https://dict.youdao.com/dictvoice?audio=anticoagulant&type=2",
      "chapter": "认知词汇 动物分类 常考生物"
    }
  ]
}