{
  "generated": "2025-11-06T22:07:53.081Z",
  "pair": 7,
  "count": 2,
  "words": [
    {
      "word": "depressed",
      "pronunciation": "/dɪˈprɛst/",
      "meanings": [
        {
          "pos": "adj.",
          "zh": "沮丧的",
          "en": "Feeling sad and unhappy for a long time."
        },
        {
          "pos": "v.",
          "zh": "压抑",
          "en": "To make someone or something less strong or powerful."
        }
      ],
      "examples": [
        {
          "en": "She felt depressed after receiving the bad news about her exam.",
          "zh": "她在收到关于考试的坏消息后感到沮丧。"
        },
        {
          "en": "The gloomy weather often makes people feel depressed and unmotivated.",
          "zh": "阴沉的天气常常让人感到沮丧和缺乏动力。"
        }
      ],
      "memoryTips": {
        "association": "Think of 'depressed' as being pressed down by heavy feelings.",
        "mnemonic": "D for down, meaning feeling low or sad."
      },
      "audioUrl": "https://dict.youdao.com/dictvoice?audio=depressed&type=2",
      "chapter": "基本词汇 形容词和副词400 Unit 5"
    },
    {
      "word": "crustal",
      "pronunciation": "/ˈkrʌstl/",
      "meanings": [
        {
          "pos": "adj.",
          "zh": "地壳的",
          "en": "Relating to the outer layer of the Earth."
        },
        {
          "pos": "adj.",
          "zh": "坚硬的",
          "en": "Describing something that is hard or solid."
        }
      ],
      "examples": [
        {
          "en": "The crustal movements caused several earthquakes last year.",
          "zh": "地壳运动导致去年发生了几次地震。"
        },
        {
          "en": "Scientists study crustal rocks to understand Earth's history.",
          "zh": "科学家研究地壳岩石以了解地球的历史。"
        }
      ],
      "memoryTips": {
        "association": "Think of 'crust' as the outer layer of a pie, similar to the Earth's crust."
      },
      "audioUrl": "https://dict.youdao.com/dictvoice?audio=crustal&type=2",
      "chapter": "认知词汇 自然分类 地震"
    }
  ]
}