{
  "generated": "2025-12-16T22:08:14.829Z",
  "pair": 2,
  "count": 2,
  "words": [
    {
      "word": "offensive",
      "pronunciation": "/əˈfɛn.sɪv/",
      "meanings": [
        {
          "pos": "adj.",
          "zh": "冒犯的",
          "en": "Causing anger or hurt feelings."
        },
        {
          "pos": "n.",
          "zh": "进攻",
          "en": "A military attack or an aggressive action."
        }
      ],
      "examples": [
        {
          "en": "His comments were considered offensive by many in the audience.",
          "zh": "他的评论被许多观众视为冒犯。"
        },
        {
          "en": "The country launched an offensive against its neighboring rival.",
          "zh": "该国对其邻国对手发起了进攻。"
        }
      ],
      "memoryTips": {},
      "audioUrl": "https://dict.youdao.com/dictvoice?audio=offensive&type=2",
      "chapter": "核心词汇 法制与犯罪 Unit 3"
    },
    {
      "word": "synthetic voice",
      "pronunciation": "/sɪnˈθɛtɪk vɔɪs/",
      "meanings": [
        {
          "pos": "n.",
          "zh": "合成语音",
          "en": "A computer-generated voice that can mimic human speech."
        },
        {
          "pos": "n.",
          "zh": "虚拟声音",
          "en": "An artificial voice used in technology for communication."
        }
      ],
      "examples": [
        {
          "en": "Many apps now use synthetic voice for reading text aloud.",
          "zh": "现在许多应用程序使用合成语音来朗读文本。"
        },
        {
          "en": "The synthetic voice technology has improved significantly over the years.",
          "zh": "合成语音技术在这些年中有了显著的改善。"
        }
      ],
      "memoryTips": {},
      "audioUrl": "https://dict.youdao.com/dictvoice?audio=synthetic%20voice&type=2",
      "chapter": "认知词汇 动物分类 动物智力与语言习得"
    }
  ]
}