{
  "generated": "2025-12-28T22:08:04.466Z",
  "pair": 7,
  "count": 2,
  "words": [
    {
      "word": "elimination",
      "pronunciation": "/ɪˌlɪməˈneɪʃən/",
      "meanings": [
        {
          "pos": "n.",
          "zh": "消除，剔除",
          "en": "The act of removing something completely."
        },
        {
          "pos": "n.",
          "zh": "淘汰",
          "en": "The process of getting rid of something that is not needed or useful."
        }
      ],
      "examples": [
        {
          "en": "The elimination of waste is crucial for a cleaner environment.",
          "zh": "消除废物对一个更清洁的环境至关重要。"
        },
        {
          "en": "They focused on the elimination of errors in the final report.",
          "zh": "他们专注于消除最终报告中的错误。"
        }
      ],
      "memoryTips": {
        "etymology": "Derived from the Latin word 'eliminare', meaning 'to remove' or 'to turn out'."
      },
      "audioUrl": "https://dict.youdao.com/dictvoice?audio=elimination&type=2",
      "chapter": "基本词汇 名词200 Unit 4"
    },
    {
      "word": "ecology",
      "pronunciation": "/ɪˈkɑːlədʒi/",
      "meanings": [
        {
          "pos": "n.",
          "zh": "生态学",
          "en": "The study of living things and their environment."
        },
        {
          "pos": "n.",
          "zh": "生态",
          "en": "The relationship between living organisms and their surroundings."
        }
      ],
      "examples": [
        {
          "en": "Ecology helps us understand how species interact with each other.",
          "zh": "生态学帮助我们理解物种之间是如何相互作用的。"
        },
        {
          "en": "Protecting ecology is essential for the survival of our planet.",
          "zh": "保护生态对我们星球的生存至关重要。"
        }
      ],
      "memoryTips": {
        "etymology": "The word 'ecology' comes from the Greek 'oikos' meaning 'house' and 'logos' meaning 'study'."
      },
      "audioUrl": "https://dict.youdao.com/dictvoice?audio=ecology&type=2",
      "chapter": "基本词汇 名词200 Unit 3"
    }
  ]
}