{
  "generated": "2026-01-02T22:08:11.445Z",
  "pair": 8,
  "count": 2,
  "words": [
    {
      "word": "commercial whaling",
      "pronunciation": "/kəˈmɜːr.ʃəl ˈweɪ.lɪŋ/",
      "meanings": [
        {
          "pos": "n.",
          "zh": "商业捕鲸",
          "en": "The practice of hunting whales for profit."
        },
        {
          "pos": "n.",
          "zh": "商业捕鲸活动",
          "en": "Activities related to the commercial hunting of whales."
        }
      ],
      "examples": [
        {
          "en": "Many countries have banned commercial whaling to protect endangered species.",
          "zh": "许多国家禁止商业捕鲸，以保护濒危物种。"
        },
        {
          "en": "Commercial whaling poses serious threats to marine ecosystems and biodiversity.",
          "zh": "商业捕鲸对海洋生态系统和生物多样性构成严重威胁。"
        }
      ],
      "memoryTips": {},
      "audioUrl": "https://dict.youdao.com/dictvoice?audio=commercial%20whaling&type=2",
      "chapter": "认知词汇 动物分类 常考生物"
    },
    {
      "word": "aeronautical engineer",
      "pronunciation": "/ˌɛəroʊˈnɔːtɪkəl ˈɛnɪdʒɪr/",
      "meanings": [
        {
          "pos": "n.",
          "zh": "航空工程师",
          "en": "An aeronautical engineer is a professional who designs aircraft and spacecraft."
        }
      ],
      "examples": [
        {
          "en": "She wants to become an aeronautical engineer after finishing her studies.",
          "zh": "她想在完成学业后成为一名航空工程师。"
        },
        {
          "en": "Aeronautical engineers work on improving flight safety and efficiency.",
          "zh": "航空工程师致力于提高飞行安全性和效率。"
        }
      ],
      "memoryTips": {},
      "audioUrl": "https://dict.youdao.com/dictvoice?audio=aeronautical%20engineer&type=2",
      "chapter": "认知词汇 动物分类 常考生物"
    }
  ]
}